MANIFEST.in
fixture_yaml.py
setup.cfg
setup.py
fixture_yaml.egg-info/PKG-INFO
fixture_yaml.egg-info/SOURCES.txt
fixture_yaml.egg-info/dependency_links.txt
fixture_yaml.egg-info/requires.txt
fixture_yaml.egg-info/top_level.txt
fixture_yaml.egg-info/zip-safe
tests/test.yml
tests/test2.yml
tests/test_yamlset.py