Metadata-Version: 1.0
Name: fixture-yaml
Version: 0.1.1
Summary: fixture-yaml is an extension that adds YAML support to fixture library
Home-page: https://bitbucket.org/w31rd0/fixture-yaml
Author: Ilya Shabalin
Author-email: ilja.shabalin@gmail.com
License: Public Domain
Platform: UNKNOWN
Classifier: Environment :: Other Environment
Classifier: Intended Audience :: Developers
Classifier: License :: Public Domain
Classifier: Operating System :: OS Independent
Classifier: Programming Language :: Python
Classifier: Topic :: Software Development :: Testing
Classifier: Topic :: Software Development :: Quality Assurance
Classifier: Topic :: Utilities
